msal_streamlit_authentication/__init__.py
msal_streamlit_authentication/frontend/dist/assets/index-4081600b.css
msal_streamlit_authentication/frontend/dist/assets/index-99fcc6ac.js
msal_streamlit_authentication/frontend/dist/index.html
msal_streamlit_authentication-1.0.8.dist-info/METADATA
msal_streamlit_authentication-1.0.8.dist-info/WHEEL
msal_streamlit_authentication-1.0.8.dist-info/RECORD
